palworld_api/__init__.py
palworld_api/palworld_api.py
palworld_api-2.0.0.dist-info/METADATA
palworld_api-2.0.0.dist-info/WHEEL
palworld_api-2.0.0.dist-info/top_level.txt
palworld_api-2.0.0.dist-info/RECORD
