Metadata-Version: 2.1
Name: palworld-api
Version: 2.0.0
Summary: A Python API wrapper for the Palworld Rest API.
Home-page: https://github.com/dkoz/palworld-api
Author: dkoz
Author-email: koz@beskor.net
Requires-Python: >=3.11
Requires-Dist: aiohttp>=3.11
